[{"name": "id_regiao", "description": "<descri\u00e7\u00e3o da coluna>", "is_in_staging": true, "is_partition": false, "type": "STRING"}, {"name": "id_mesorregiao", "description": "<descri\u00e7\u00e3o da coluna>", "is_in_staging": true, "is_partition": false, "type": "STRING"}, {"name": "id_microrregiao", "description": "<descri\u00e7\u00e3o da coluna>", "is_in_staging": true, "is_partition": false, "type": "STRING"}, {"name": "id_regiao_metropolitana", "description": "<descri\u00e7\u00e3o da coluna>", "is_in_staging": true, "is_partition": false, "type": "STRING"}, {"name": "id_municipio", "description": "<descri\u00e7\u00e3o da coluna>", "is_in_staging": true, "is_partition": false, "type": "STRING"}, {"name": "area_ponderacao", "description": "<descri\u00e7\u00e3o da coluna>", "is_in_staging": true, "is_partition": false, "type": "STRING"}, {"name": "situacao_setor", "description": "<descri\u00e7\u00e3o da coluna>", "is_in_staging": true, "is_partition": false, "type": "STRING"}, {"name": "situacao_domicilio", "description": "<descri\u00e7\u00e3o da coluna>", "is_in_staging": true, "is_partition": false, "type": "STRING"}, {"name": "controle", "description": "<descri\u00e7\u00e3o da coluna>", "is_in_staging": true, "is_partition": false, "type": "STRING"}, {"name": "numero_ordem", "description": "<descri\u00e7\u00e3o da coluna>", "is_in_staging": true, "is_partition": false, "type": "STRING"}, {"name": "peso_amostral", "description": "<descri\u00e7\u00e3o da coluna>", "is_in_staging": true, "is_partition": false, "type": "STRING"}, {"name": "v0502", "description": "<descri\u00e7\u00e3o da coluna>", "is_in_staging": true, "is_partition": false, "type": "STRING"}, {"name": "v0601", "description": "<descri\u00e7\u00e3o da coluna>", "is_in_staging": true, "is_partition": false, "type": "STRING"}, {"name": "v6033", "description": "<descri\u00e7\u00e3o da coluna>", "is_in_staging": true, "is_partition": false, "type": "STRING"}, {"name": "v6036", "description": "<descri\u00e7\u00e3o da coluna>", "is_in_staging": true, "is_partition": false, "type": "STRING"}, {"name": "v6037", "description": "<descri\u00e7\u00e3o da coluna>", "is_in_staging": true, "is_partition": false, "type": "STRING"}, {"name": "v6040", "description": "<descri\u00e7\u00e3o da coluna>", "is_in_staging": true, "is_partition": false, "type": "STRING"}, {"name": "v0606", "description": "<descri\u00e7\u00e3o da coluna>", "is_in_staging": true, "is_partition": false, "type": "STRING"}, {"name": "v0613", "description": "<descri\u00e7\u00e3o da coluna>", "is_in_staging": true, "is_partition": false, "type": "STRING"}, {"name": "v0614", "description": "<descri\u00e7\u00e3o da coluna>", "is_in_staging": true, "is_partition": false, "type": "STRING"}, {"name": "v0615", "description": "<descri\u00e7\u00e3o da coluna>", "is_in_staging": true, "is_partition": false, "type": "STRING"}, {"name": "v0616", "description": "<descri\u00e7\u00e3o da coluna>", "is_in_staging": true, "is_partition": false, "type": "STRING"}, {"name": "v0617", "description": "<descri\u00e7\u00e3o da coluna>", "is_in_staging": true, "is_partition": false, "type": "STRING"}, {"name": "v0618", "description": "<descri\u00e7\u00e3o da coluna>", "is_in_staging": true, "is_partition": false, "type": "STRING"}, {"name": "v0619", "description": "<descri\u00e7\u00e3o da coluna>", "is_in_staging": true, "is_partition": false, "type": "STRING"}, {"name": "v0620", "description": "<descri\u00e7\u00e3o da coluna>", "is_in_staging": true, "is_partition": false, "type": "STRING"}, {"name": "v0621", "description": "<descri\u00e7\u00e3o da coluna>", "is_in_staging": true, "is_partition": false, "type": "STRING"}, {"name": "v0622", "description": "<descri\u00e7\u00e3o da coluna>", "is_in_staging": true, "is_partition": false, "type": "STRING"}, {"name": "v6222", "description": "<descri\u00e7\u00e3o da coluna>", "is_in_staging": true, "is_partition": false, "type": "STRING"}, {"name": "v6224", "description": "<descri\u00e7\u00e3o da coluna>", "is_in_staging": true, "is_partition": false, "type": "STRING"}, {"name": "v0623", "description": "<descri\u00e7\u00e3o da coluna>", "is_in_staging": true, "is_partition": false, "type": "STRING"}, {"name": "v0624", "description": "<descri\u00e7\u00e3o da coluna>", "is_in_staging": true, "is_partition": false, "type": "STRING"}, {"name": "v0625", "description": "<descri\u00e7\u00e3o da coluna>", "is_in_staging": true, "is_partition": false, "type": "STRING"}, {"name": "v6252", "description": "<descri\u00e7\u00e3o da coluna>", "is_in_staging": true, "is_partition": false, "type": "STRING"}, {"name": "v6254", "description": "<descri\u00e7\u00e3o da coluna>", "is_in_staging": true, "is_partition": false, "type": "STRING"}, {"name": "v6256", "description": "<descri\u00e7\u00e3o da coluna>", "is_in_staging": true, "is_partition": false, "type": "STRING"}, {"name": "v0626", "description": "<descri\u00e7\u00e3o da coluna>", "is_in_staging": true, "is_partition": false, "type": "STRING"}, {"name": "v6262", "description": "<descri\u00e7\u00e3o da coluna>", "is_in_staging": true, "is_partition": false, "type": "STRING"}, {"name": "v6264", "description": "<descri\u00e7\u00e3o da coluna>", "is_in_staging": true, "is_partition": false, "type": "STRING"}, {"name": "v6266", "description": "<descri\u00e7\u00e3o da coluna>", "is_in_staging": true, "is_partition": false, "type": "STRING"}, {"name": "v0627", "description": "<descri\u00e7\u00e3o da coluna>", "is_in_staging": true, "is_partition": false, "type": "STRING"}, {"name": "v0628", "description": "<descri\u00e7\u00e3o da coluna>", "is_in_staging": true, "is_partition": false, "type": "STRING"}, {"name": "v0629", "description": "<descri\u00e7\u00e3o da coluna>", "is_in_staging": true, "is_partition": false, "type": "STRING"}, {"name": "v0630", "description": "<descri\u00e7\u00e3o da coluna>", "is_in_staging": true, "is_partition": false, "type": "STRING"}, {"name": "v0631", "description": "<descri\u00e7\u00e3o da coluna>", "is_in_staging": true, "is_partition": false, "type": "STRING"}, {"name": "v0632", "description": "<descri\u00e7\u00e3o da coluna>", "is_in_staging": true, "is_partition": false, "type": "STRING"}, {"name": "v0633", "description": "<descri\u00e7\u00e3o da coluna>", "is_in_staging": true, "is_partition": false, "type": "STRING"}, {"name": "v0634", "description": "<descri\u00e7\u00e3o da coluna>", "is_in_staging": true, "is_partition": false, "type": "STRING"}, {"name": "v0635", "description": "<descri\u00e7\u00e3o da coluna>", "is_in_staging": true, "is_partition": false, "type": "STRING"}, {"name": "v6400", "description": "<descri\u00e7\u00e3o da coluna>", "is_in_staging": true, "is_partition": false, "type": "STRING"}, {"name": "v6352", "description": "<descri\u00e7\u00e3o da coluna>", "is_in_staging": true, "is_partition": false, "type": "STRING"}, {"name": "v6354", "description": "<descri\u00e7\u00e3o da coluna>", "is_in_staging": true, "is_partition": false, "type": "STRING"}, {"name": "v6356", "description": "<descri\u00e7\u00e3o da coluna>", "is_in_staging": true, "is_partition": false, "type": "STRING"}, {"name": "v0636", "description": "<descri\u00e7\u00e3o da coluna>", "is_in_staging": true, "is_partition": false, "type": "STRING"}, {"name": "v6362", "description": "<descri\u00e7\u00e3o da coluna>", "is_in_staging": true, "is_partition": false, "type": "STRING"}, {"name": "v6364", "description": "<descri\u00e7\u00e3o da coluna>", "is_in_staging": true, "is_partition": false, "type": "STRING"}, {"name": "v6366", "description": "<descri\u00e7\u00e3o da coluna>", "is_in_staging": true, "is_partition": false, "type": "STRING"}, {"name": "v0637", "description": "<descri\u00e7\u00e3o da coluna>", "is_in_staging": true, "is_partition": false, "type": "STRING"}, {"name": "v0638", "description": "<descri\u00e7\u00e3o da coluna>", "is_in_staging": true, "is_partition": false, "type": "STRING"}, {"name": "v0639", "description": "<descri\u00e7\u00e3o da coluna>", "is_in_staging": true, "is_partition": false, "type": "STRING"}, {"name": "v0640", "description": "<descri\u00e7\u00e3o da coluna>", "is_in_staging": true, "is_partition": false, "type": "STRING"}, {"name": "v0641", "description": "<descri\u00e7\u00e3o da coluna>", "is_in_staging": true, "is_partition": false, "type": "STRING"}, {"name": "v0642", "description": "<descri\u00e7\u00e3o da coluna>", "is_in_staging": true, "is_partition": false, "type": "STRING"}, {"name": "v0643", "description": "<descri\u00e7\u00e3o da coluna>", "is_in_staging": true, "is_partition": false, "type": "STRING"}, {"name": "v0644", "description": "<descri\u00e7\u00e3o da coluna>", "is_in_staging": true, "is_partition": false, "type": "STRING"}, {"name": "v0645", "description": "<descri\u00e7\u00e3o da coluna>", "is_in_staging": true, "is_partition": false, "type": "STRING"}, {"name": "v6461", "description": "<descri\u00e7\u00e3o da coluna>", "is_in_staging": true, "is_partition": false, "type": "STRING"}, {"name": "v6471", "description": "<descri\u00e7\u00e3o da coluna>", "is_in_staging": true, "is_partition": false, "type": "STRING"}, {"name": "v0648", "description": "<descri\u00e7\u00e3o da coluna>", "is_in_staging": true, "is_partition": false, "type": "STRING"}, {"name": "v0649", "description": "<descri\u00e7\u00e3o da coluna>", "is_in_staging": true, "is_partition": false, "type": "STRING"}, {"name": "v0650", "description": "<descri\u00e7\u00e3o da coluna>", "is_in_staging": true, "is_partition": false, "type": "STRING"}, {"name": "v0651", "description": "<descri\u00e7\u00e3o da coluna>", "is_in_staging": true, "is_partition": false, "type": "STRING"}, {"name": "v6511", "description": "<descri\u00e7\u00e3o da coluna>", "is_in_staging": true, "is_partition": false, "type": "STRING"}, {"name": "v6513", "description": "<descri\u00e7\u00e3o da coluna>", "is_in_staging": true, "is_partition": false, "type": "STRING"}, {"name": "v6514", "description": "<descri\u00e7\u00e3o da coluna>", "is_in_staging": true, "is_partition": false, "type": "STRING"}, {"name": "v0652", "description": "<descri\u00e7\u00e3o da coluna>", "is_in_staging": true, "is_partition": false, "type": "STRING"}, {"name": "v6521", "description": "<descri\u00e7\u00e3o da coluna>", "is_in_staging": true, "is_partition": false, "type": "STRING"}, {"name": "v6524", "description": "<descri\u00e7\u00e3o da coluna>", "is_in_staging": true, "is_partition": false, "type": "STRING"}, {"name": "v6525", "description": "<descri\u00e7\u00e3o da coluna>", "is_in_staging": true, "is_partition": false, "type": "STRING"}, {"name": "v6526", "description": "<descri\u00e7\u00e3o da coluna>", "is_in_staging": true, "is_partition": false, "type": "STRING"}, {"name": "v6527", "description": "<descri\u00e7\u00e3o da coluna>", "is_in_staging": true, "is_partition": false, "type": "STRING"}, {"name": "v6528", "description": "<descri\u00e7\u00e3o da coluna>", "is_in_staging": true, "is_partition": false, "type": "STRING"}, {"name": "v6529", "description": "<descri\u00e7\u00e3o da coluna>", "is_in_staging": true, "is_partition": false, "type": "STRING"}, {"name": "v6530", "description": "<descri\u00e7\u00e3o da coluna>", "is_in_staging": true, "is_partition": false, "type": "STRING"}, {"name": "v6531", "description": "<descri\u00e7\u00e3o da coluna>", "is_in_staging": true, "is_partition": false, "type": "STRING"}, {"name": "v6532", "description": "<descri\u00e7\u00e3o da coluna>", "is_in_staging": true, "is_partition": false, "type": "STRING"}, {"name": "v0653", "description": "<descri\u00e7\u00e3o da coluna>", "is_in_staging": true, "is_partition": false, "type": "STRING"}, {"name": "v0654", "description": "<descri\u00e7\u00e3o da coluna>", "is_in_staging": true, "is_partition": false, "type": "STRING"}, {"name": "v0655", "description": "<descri\u00e7\u00e3o da coluna>", "is_in_staging": true, "is_partition": false, "type": "STRING"}, {"name": "v0656", "description": "<descri\u00e7\u00e3o da coluna>", "is_in_staging": true, "is_partition": false, "type": "STRING"}, {"name": "v0657", "description": "<descri\u00e7\u00e3o da coluna>", "is_in_staging": true, "is_partition": false, "type": "STRING"}, {"name": "v0658", "description": "<descri\u00e7\u00e3o da coluna>", "is_in_staging": true, "is_partition": false, "type": "STRING"}, {"name": "v0659", "description": "<descri\u00e7\u00e3o da coluna>", "is_in_staging": true, "is_partition": false, "type": "STRING"}, {"name": "v6591", "description": "<descri\u00e7\u00e3o da coluna>", "is_in_staging": true, "is_partition": false, "type": "STRING"}, {"name": "v0660", "description": "<descri\u00e7\u00e3o da coluna>", "is_in_staging": true, "is_partition": false, "type": "STRING"}, {"name": "v6602", "description": "<descri\u00e7\u00e3o da coluna>", "is_in_staging": true, "is_partition": false, "type": "STRING"}, {"name": "v6604", "description": "<descri\u00e7\u00e3o da coluna>", "is_in_staging": true, "is_partition": false, "type": "STRING"}, {"name": "v6606", "description": "<descri\u00e7\u00e3o da coluna>", "is_in_staging": true, "is_partition": false, "type": "STRING"}, {"name": "v0661", "description": "<descri\u00e7\u00e3o da coluna>", "is_in_staging": true, "is_partition": false, "type": "STRING"}, {"name": "v0662", "description": "<descri\u00e7\u00e3o da coluna>", "is_in_staging": true, "is_partition": false, "type": "STRING"}, {"name": "v0663", "description": "<descri\u00e7\u00e3o da coluna>", "is_in_staging": true, "is_partition": false, "type": "STRING"}, {"name": "v6631", "description": "<descri\u00e7\u00e3o da coluna>", "is_in_staging": true, "is_partition": false, "type": "STRING"}, {"name": "v6632", "description": "<descri\u00e7\u00e3o da coluna>", "is_in_staging": true, "is_partition": false, "type": "STRING"}, {"name": "v6633", "description": "<descri\u00e7\u00e3o da coluna>", "is_in_staging": true, "is_partition": false, "type": "STRING"}, {"name": "v0664", "description": "<descri\u00e7\u00e3o da coluna>", "is_in_staging": true, "is_partition": false, "type": "STRING"}, {"name": "v6641", "description": "<descri\u00e7\u00e3o da coluna>", "is_in_staging": true, "is_partition": false, "type": "STRING"}, {"name": "v6642", "description": "<descri\u00e7\u00e3o da coluna>", "is_in_staging": true, "is_partition": false, "type": "STRING"}, {"name": "v6643", "description": "<descri\u00e7\u00e3o da coluna>", "is_in_staging": true, "is_partition": false, "type": "STRING"}, {"name": "v0665", "description": "<descri\u00e7\u00e3o da coluna>", "is_in_staging": true, "is_partition": false, "type": "STRING"}, {"name": "v6660", "description": "<descri\u00e7\u00e3o da coluna>", "is_in_staging": true, "is_partition": false, "type": "STRING"}, {"name": "v6664", "description": "<descri\u00e7\u00e3o da coluna>", "is_in_staging": true, "is_partition": false, "type": "STRING"}, {"name": "v0667", "description": "<descri\u00e7\u00e3o da coluna>", "is_in_staging": true, "is_partition": false, "type": "STRING"}, {"name": "v0668", "description": "<descri\u00e7\u00e3o da coluna>", "is_in_staging": true, "is_partition": false, "type": "STRING"}, {"name": "v6681", "description": "<descri\u00e7\u00e3o da coluna>", "is_in_staging": true, "is_partition": false, "type": "STRING"}, {"name": "v6682", "description": "<descri\u00e7\u00e3o da coluna>", "is_in_staging": true, "is_partition": false, "type": "STRING"}, {"name": "v0669", "description": "<descri\u00e7\u00e3o da coluna>", "is_in_staging": true, "is_partition": false, "type": "STRING"}, {"name": "v6691", "description": "<descri\u00e7\u00e3o da coluna>", "is_in_staging": true, "is_partition": false, "type": "STRING"}, {"name": "v6692", "description": "<descri\u00e7\u00e3o da coluna>", "is_in_staging": true, "is_partition": false, "type": "STRING"}, {"name": "v6693", "description": "<descri\u00e7\u00e3o da coluna>", "is_in_staging": true, "is_partition": false, "type": "STRING"}, {"name": "v6800", "description": "<descri\u00e7\u00e3o da coluna>", "is_in_staging": true, "is_partition": false, "type": "STRING"}, {"name": "v0670", "description": "<descri\u00e7\u00e3o da coluna>", "is_in_staging": true, "is_partition": false, "type": "STRING"}, {"name": "v0671", "description": "<descri\u00e7\u00e3o da coluna>", "is_in_staging": true, "is_partition": false, "type": "STRING"}, {"name": "v6900", "description": "<descri\u00e7\u00e3o da coluna>", "is_in_staging": true, "is_partition": false, "type": "STRING"}, {"name": "v6910", "description": "<descri\u00e7\u00e3o da coluna>", "is_in_staging": true, "is_partition": false, "type": "STRING"}, {"name": "v6920", "description": "<descri\u00e7\u00e3o da coluna>", "is_in_staging": true, "is_partition": false, "type": "STRING"}, {"name": "v6930", "description": "<descri\u00e7\u00e3o da coluna>", "is_in_staging": true, "is_partition": false, "type": "STRING"}, {"name": "v6940", "description": "<descri\u00e7\u00e3o da coluna>", "is_in_staging": true, "is_partition": false, "type": "STRING"}, {"name": "v6121", "description": "<descri\u00e7\u00e3o da coluna>", "is_in_staging": true, "is_partition": false, "type": "STRING"}, {"name": "v0604", "description": "<descri\u00e7\u00e3o da coluna>", "is_in_staging": true, "is_partition": false, "type": "STRING"}, {"name": "v0605", "description": "<descri\u00e7\u00e3o da coluna>", "is_in_staging": true, "is_partition": false, "type": "STRING"}, {"name": "v5020", "description": "<descri\u00e7\u00e3o da coluna>", "is_in_staging": true, "is_partition": false, "type": "STRING"}, {"name": "v5060", "description": "<descri\u00e7\u00e3o da coluna>", "is_in_staging": true, "is_partition": false, "type": "STRING"}, {"name": "v5070", "description": "<descri\u00e7\u00e3o da coluna>", "is_in_staging": true, "is_partition": false, "type": "STRING"}, {"name": "v5080", "description": "<descri\u00e7\u00e3o da coluna>", "is_in_staging": true, "is_partition": false, "type": "STRING"}, {"name": "v6462", "description": "<descri\u00e7\u00e3o da coluna>", "is_in_staging": true, "is_partition": false, "type": "STRING"}, {"name": "v6472", "description": "<descri\u00e7\u00e3o da coluna>", "is_in_staging": true, "is_partition": false, "type": "STRING"}, {"name": "v5110", "description": "<descri\u00e7\u00e3o da coluna>", "is_in_staging": true, "is_partition": false, "type": "STRING"}, {"name": "v5120", "description": "<descri\u00e7\u00e3o da coluna>", "is_in_staging": true, "is_partition": false, "type": "STRING"}, {"name": "v5030", "description": "<descri\u00e7\u00e3o da coluna>", "is_in_staging": true, "is_partition": false, "type": "STRING"}, {"name": "v5040", "description": "<descri\u00e7\u00e3o da coluna>", "is_in_staging": true, "is_partition": false, "type": "STRING"}, {"name": "v5090", "description": "<descri\u00e7\u00e3o da coluna>", "is_in_staging": true, "is_partition": false, "type": "STRING"}, {"name": "v5100", "description": "<descri\u00e7\u00e3o da coluna>", "is_in_staging": true, "is_partition": false, "type": "STRING"}, {"name": "v5130", "description": "<descri\u00e7\u00e3o da coluna>", "is_in_staging": true, "is_partition": false, "type": "STRING"}, {"name": "m0502", "description": "<descri\u00e7\u00e3o da coluna>", "is_in_staging": true, "is_partition": false, "type": "STRING"}, {"name": "m0601", "description": "<descri\u00e7\u00e3o da coluna>", "is_in_staging": true, "is_partition": false, "type": "STRING"}, {"name": "m6033", "description": "<descri\u00e7\u00e3o da coluna>", "is_in_staging": true, "is_partition": false, "type": "STRING"}, {"name": "m0606", "description": "<descri\u00e7\u00e3o da coluna>", "is_in_staging": true, "is_partition": false, "type": "STRING"}, {"name": "m0613", "description": "<descri\u00e7\u00e3o da coluna>", "is_in_staging": true, "is_partition": false, "type": "STRING"}, {"name": "m0614", "description": "<descri\u00e7\u00e3o da coluna>", "is_in_staging": true, "is_partition": false, "type": "STRING"}, {"name": "m0615", "description": "<descri\u00e7\u00e3o da coluna>", "is_in_staging": true, "is_partition": false, "type": "STRING"}, {"name": "m0616", "description": "<descri\u00e7\u00e3o da coluna>", "is_in_staging": true, "is_partition": false, "type": "STRING"}, {"name": "m0617", "description": "<descri\u00e7\u00e3o da coluna>", "is_in_staging": true, "is_partition": false, "type": "STRING"}, {"name": "m0618", "description": "<descri\u00e7\u00e3o da coluna>", "is_in_staging": true, "is_partition": false, "type": "STRING"}, {"name": "m0619", "description": "<descri\u00e7\u00e3o da coluna>", "is_in_staging": true, "is_partition": false, "type": "STRING"}, {"name": "m0620", "description": "<descri\u00e7\u00e3o da coluna>", "is_in_staging": true, "is_partition": false, "type": "STRING"}, {"name": "m0621", "description": "<descri\u00e7\u00e3o da coluna>", "is_in_staging": true, "is_partition": false, "type": "STRING"}, {"name": "m0622", "description": "<descri\u00e7\u00e3o da coluna>", "is_in_staging": true, "is_partition": false, "type": "STRING"}, {"name": "m6222", "description": "<descri\u00e7\u00e3o da coluna>", "is_in_staging": true, "is_partition": false, "type": "STRING"}, {"name": "m6224", "description": "<descri\u00e7\u00e3o da coluna>", "is_in_staging": true, "is_partition": false, "type": "STRING"}, {"name": "m0623", "description": "<descri\u00e7\u00e3o da coluna>", "is_in_staging": true, "is_partition": false, "type": "STRING"}, {"name": "m0624", "description": "<descri\u00e7\u00e3o da coluna>", "is_in_staging": true, "is_partition": false, "type": "STRING"}, {"name": "m0625", "description": "<descri\u00e7\u00e3o da coluna>", "is_in_staging": true, "is_partition": false, "type": "STRING"}, {"name": "m6252", "description": "<descri\u00e7\u00e3o da coluna>", "is_in_staging": true, "is_partition": false, "type": "STRING"}, {"name": "m6254", "description": "<descri\u00e7\u00e3o da coluna>", "is_in_staging": true, "is_partition": false, "type": "STRING"}, {"name": "m6256", "description": "<descri\u00e7\u00e3o da coluna>", "is_in_staging": true, "is_partition": false, "type": "STRING"}, {"name": "m0626", "description": "<descri\u00e7\u00e3o da coluna>", "is_in_staging": true, "is_partition": false, "type": "STRING"}, {"name": "m6262", "description": "<descri\u00e7\u00e3o da coluna>", "is_in_staging": true, "is_partition": false, "type": "STRING"}, {"name": "m6264", "description": "<descri\u00e7\u00e3o da coluna>", "is_in_staging": true, "is_partition": false, "type": "STRING"}, {"name": "m6266", "description": "<descri\u00e7\u00e3o da coluna>", "is_in_staging": true, "is_partition": false, "type": "STRING"}, {"name": "m0627", "description": "<descri\u00e7\u00e3o da coluna>", "is_in_staging": true, "is_partition": false, "type": "STRING"}, {"name": "m0628", "description": "<descri\u00e7\u00e3o da coluna>", "is_in_staging": true, "is_partition": false, "type": "STRING"}, {"name": "m0629", "description": "<descri\u00e7\u00e3o da coluna>", "is_in_staging": true, "is_partition": false, "type": "STRING"}, {"name": "m0630", "description": "<descri\u00e7\u00e3o da coluna>", "is_in_staging": true, "is_partition": false, "type": "STRING"}, {"name": "m0631", "description": "<descri\u00e7\u00e3o da coluna>", "is_in_staging": true, "is_partition": false, "type": "STRING"}, {"name": "m0632", "description": "<descri\u00e7\u00e3o da coluna>", "is_in_staging": true, "is_partition": false, "type": "STRING"}, {"name": "m0633", "description": "<descri\u00e7\u00e3o da coluna>", "is_in_staging": true, "is_partition": false, "type": "STRING"}, {"name": "m0634", "description": "<descri\u00e7\u00e3o da coluna>", "is_in_staging": true, "is_partition": false, "type": "STRING"}, {"name": "m0635", "description": "<descri\u00e7\u00e3o da coluna>", "is_in_staging": true, "is_partition": false, "type": "STRING"}, {"name": "m6352", "description": "<descri\u00e7\u00e3o da coluna>", "is_in_staging": true, "is_partition": false, "type": "STRING"}, {"name": "m6354", "description": "<descri\u00e7\u00e3o da coluna>", "is_in_staging": true, "is_partition": false, "type": "STRING"}, {"name": "m6356", "description": "<descri\u00e7\u00e3o da coluna>", "is_in_staging": true, "is_partition": false, "type": "STRING"}, {"name": "m0636", "description": "<descri\u00e7\u00e3o da coluna>", "is_in_staging": true, "is_partition": false, "type": "STRING"}, {"name": "m6362", "description": "<descri\u00e7\u00e3o da coluna>", "is_in_staging": true, "is_partition": false, "type": "STRING"}, {"name": "m6364", "description": "<descri\u00e7\u00e3o da coluna>", "is_in_staging": true, "is_partition": false, "type": "STRING"}, {"name": "m6366", "description": "<descri\u00e7\u00e3o da coluna>", "is_in_staging": true, "is_partition": false, "type": "STRING"}, {"name": "m0637", "description": "<descri\u00e7\u00e3o da coluna>", "is_in_staging": true, "is_partition": false, "type": "STRING"}, {"name": "m0638", "description": "<descri\u00e7\u00e3o da coluna>", "is_in_staging": true, "is_partition": false, "type": "STRING"}, {"name": "m0639", "description": "<descri\u00e7\u00e3o da coluna>", "is_in_staging": true, "is_partition": false, "type": "STRING"}, {"name": "m0640", "description": "<descri\u00e7\u00e3o da coluna>", "is_in_staging": true, "is_partition": false, "type": "STRING"}, {"name": "m0641", "description": "<descri\u00e7\u00e3o da coluna>", "is_in_staging": true, "is_partition": false, "type": "STRING"}, {"name": "m0642", "description": "<descri\u00e7\u00e3o da coluna>", "is_in_staging": true, "is_partition": false, "type": "STRING"}, {"name": "m0643", "description": "<descri\u00e7\u00e3o da coluna>", "is_in_staging": true, "is_partition": false, "type": "STRING"}, {"name": "m0644", "description": "<descri\u00e7\u00e3o da coluna>", "is_in_staging": true, "is_partition": false, "type": "STRING"}, {"name": "m0645", "description": "<descri\u00e7\u00e3o da coluna>", "is_in_staging": true, "is_partition": false, "type": "STRING"}, {"name": "m6461", "description": "<descri\u00e7\u00e3o da coluna>", "is_in_staging": true, "is_partition": false, "type": "STRING"}, {"name": "m6471", "description": "<descri\u00e7\u00e3o da coluna>", "is_in_staging": true, "is_partition": false, "type": "STRING"}, {"name": "m0648", "description": "<descri\u00e7\u00e3o da coluna>", "is_in_staging": true, "is_partition": false, "type": "STRING"}, {"name": "m0649", "description": "<descri\u00e7\u00e3o da coluna>", "is_in_staging": true, "is_partition": false, "type": "STRING"}, {"name": "m0650", "description": "<descri\u00e7\u00e3o da coluna>", "is_in_staging": true, "is_partition": false, "type": "STRING"}, {"name": "m0651", "description": "<descri\u00e7\u00e3o da coluna>", "is_in_staging": true, "is_partition": false, "type": "STRING"}, {"name": "m6511", "description": "<descri\u00e7\u00e3o da coluna>", "is_in_staging": true, "is_partition": false, "type": "STRING"}, {"name": "m0652", "description": "<descri\u00e7\u00e3o da coluna>", "is_in_staging": true, "is_partition": false, "type": "STRING"}, {"name": "m6521", "description": "<descri\u00e7\u00e3o da coluna>", "is_in_staging": true, "is_partition": false, "type": "STRING"}, {"name": "m0653", "description": "<descri\u00e7\u00e3o da coluna>", "is_in_staging": true, "is_partition": false, "type": "STRING"}, {"name": "m0654", "description": "<descri\u00e7\u00e3o da coluna>", "is_in_staging": true, "is_partition": false, "type": "STRING"}, {"name": "m0655", "description": "<descri\u00e7\u00e3o da coluna>", "is_in_staging": true, "is_partition": false, "type": "STRING"}, {"name": "m0656", "description": "<descri\u00e7\u00e3o da coluna>", "is_in_staging": true, "is_partition": false, "type": "STRING"}, {"name": "m0657", "description": "<descri\u00e7\u00e3o da coluna>", "is_in_staging": true, "is_partition": false, "type": "STRING"}, {"name": "m0658", "description": "<descri\u00e7\u00e3o da coluna>", "is_in_staging": true, "is_partition": false, "type": "STRING"}, {"name": "m0659", "description": "<descri\u00e7\u00e3o da coluna>", "is_in_staging": true, "is_partition": false, "type": "STRING"}, {"name": "m6591", "description": "<descri\u00e7\u00e3o da coluna>", "is_in_staging": true, "is_partition": false, "type": "STRING"}, {"name": "m0660", "description": "<descri\u00e7\u00e3o da coluna>", "is_in_staging": true, "is_partition": false, "type": "STRING"}, {"name": "m6602", "description": "<descri\u00e7\u00e3o da coluna>", "is_in_staging": true, "is_partition": false, "type": "STRING"}, {"name": "m6604", "description": "<descri\u00e7\u00e3o da coluna>", "is_in_staging": true, "is_partition": false, "type": "STRING"}, {"name": "m6606", "description": "<descri\u00e7\u00e3o da coluna>", "is_in_staging": true, "is_partition": false, "type": "STRING"}, {"name": "m0661", "description": "<descri\u00e7\u00e3o da coluna>", "is_in_staging": true, "is_partition": false, "type": "STRING"}, {"name": "m0662", "description": "<descri\u00e7\u00e3o da coluna>", "is_in_staging": true, "is_partition": false, "type": "STRING"}, {"name": "m0663", "description": "<descri\u00e7\u00e3o da coluna>", "is_in_staging": true, "is_partition": false, "type": "STRING"}, {"name": "m6631", "description": "<descri\u00e7\u00e3o da coluna>", "is_in_staging": true, "is_partition": false, "type": "STRING"}, {"name": "m6632", "description": "<descri\u00e7\u00e3o da coluna>", "is_in_staging": true, "is_partition": false, "type": "STRING"}, {"name": "m6633", "description": "<descri\u00e7\u00e3o da coluna>", "is_in_staging": true, "is_partition": false, "type": "STRING"}, {"name": "m0664", "description": "<descri\u00e7\u00e3o da coluna>", "is_in_staging": true, "is_partition": false, "type": "STRING"}, {"name": "m6641", "description": "<descri\u00e7\u00e3o da coluna>", "is_in_staging": true, "is_partition": false, "type": "STRING"}, {"name": "m6642", "description": "<descri\u00e7\u00e3o da coluna>", "is_in_staging": true, "is_partition": false, "type": "STRING"}, {"name": "m6643", "description": "<descri\u00e7\u00e3o da coluna>", "is_in_staging": true, "is_partition": false, "type": "STRING"}, {"name": "m0665", "description": "<descri\u00e7\u00e3o da coluna>", "is_in_staging": true, "is_partition": false, "type": "STRING"}, {"name": "m6660", "description": "<descri\u00e7\u00e3o da coluna>", "is_in_staging": true, "is_partition": false, "type": "STRING"}, {"name": "m0667", "description": "<descri\u00e7\u00e3o da coluna>", "is_in_staging": true, "is_partition": false, "type": "STRING"}, {"name": "m0668", "description": "<descri\u00e7\u00e3o da coluna>", "is_in_staging": true, "is_partition": false, "type": "STRING"}, {"name": "m6681", "description": "<descri\u00e7\u00e3o da coluna>", "is_in_staging": true, "is_partition": false, "type": "STRING"}, {"name": "m6682", "description": "<descri\u00e7\u00e3o da coluna>", "is_in_staging": true, "is_partition": false, "type": "STRING"}, {"name": "m0669", "description": "<descri\u00e7\u00e3o da coluna>", "is_in_staging": true, "is_partition": false, "type": "STRING"}, {"name": "m6691", "description": "<descri\u00e7\u00e3o da coluna>", "is_in_staging": true, "is_partition": false, "type": "STRING"}, {"name": "m6692", "description": "<descri\u00e7\u00e3o da coluna>", "is_in_staging": true, "is_partition": false, "type": "STRING"}, {"name": "m6693", "description": "<descri\u00e7\u00e3o da coluna>", "is_in_staging": true, "is_partition": false, "type": "STRING"}, {"name": "m0670", "description": "<descri\u00e7\u00e3o da coluna>", "is_in_staging": true, "is_partition": false, "type": "STRING"}, {"name": "m0671", "description": "<descri\u00e7\u00e3o da coluna>", "is_in_staging": true, "is_partition": false, "type": "STRING"}, {"name": "m6800", "description": "<descri\u00e7\u00e3o da coluna>", "is_in_staging": true, "is_partition": false, "type": "STRING"}, {"name": "m6121", "description": "<descri\u00e7\u00e3o da coluna>", "is_in_staging": true, "is_partition": false, "type": "STRING"}, {"name": "m0604", "description": "<descri\u00e7\u00e3o da coluna>", "is_in_staging": true, "is_partition": false, "type": "STRING"}, {"name": "m0605", "description": "<descri\u00e7\u00e3o da coluna>", "is_in_staging": true, "is_partition": false, "type": "STRING"}, {"name": "m6462", "description": "<descri\u00e7\u00e3o da coluna>", "is_in_staging": true, "is_partition": false, "type": "STRING"}, {"name": "m6472", "description": "<descri\u00e7\u00e3o da coluna>", "is_in_staging": true, "is_partition": false, "type": "STRING"}]