[{"name": "cnae_1", "description": "Classifica\u00e7\u00e3o Nacional de Atividades Econ\u00f4micas (CNAE) 1.0", "is_in_staging": true, "is_partition": false, "type": "STRING", "mode": "NULLABLE"}, {"name": "descricao", "description": "Descri\u00e7\u00e3o da CNAE 1.0", "is_in_staging": true, "is_partition": false, "type": "STRING", "mode": "NULLABLE"}, {"name": "grupo", "description": "Grupo", "is_in_staging": true, "is_partition": false, "type": "STRING", "mode": "NULLABLE"}, {"name": "descricao_grupo", "description": "Descri\u00e7\u00e3o do Grupo", "is_in_staging": true, "is_partition": false, "type": "STRING", "mode": "NULLABLE"}, {"name": "divisao", "description": "Divis\u00e3o", "is_in_staging": true, "is_partition": false, "type": "STRING", "mode": "NULLABLE"}, {"name": "descricao_divisao", "description": "Descri\u00e7\u00e3o da Divis\u00e3o", "is_in_staging": true, "is_partition": false, "type": "STRING", "mode": "NULLABLE"}, {"name": "secao", "description": "Se\u00e7\u00e3o", "is_in_staging": true, "is_partition": false, "type": "STRING", "mode": "NULLABLE"}, {"name": "descricao_secao", "description": "Descri\u00e7\u00e3o da Se\u00e7\u00e3o", "is_in_staging": true, "is_partition": false, "type": "STRING", "mode": "NULLABLE"}]