[{"name": "id_setor_censitario", "description": "Identificador do setor censit\u00e1rio", "is_in_staging": true, "is_partition": false, "type": "STRING", "mode": "NULLABLE"}, {"name": "zona", "description": "Zona", "is_in_staging": true, "is_partition": false, "type": "STRING", "mode": "NULLABLE"}, {"name": "id_uf", "description": "ID da Unidade da Federa\u00e7\u00e3o", "is_in_staging": true, "is_partition": false, "type": "STRING", "mode": "NULLABLE"}, {"name": "id_municipio", "description": "Identificador do munic\u00edpio IBGE", "is_in_staging": true, "is_partition": false, "type": "STRING", "mode": "NULLABLE"}, {"name": "nome_municipio", "description": "Nome do munic\u00edpio", "is_in_staging": true, "is_partition": false, "type": "STRING", "mode": "NULLABLE"}, {"name": "id_vizinhanca", "description": "Identificador da vizinhan\u00e7a", "is_in_staging": true, "is_partition": false, "type": "STRING", "mode": "NULLABLE"}, {"name": "nome_vizinhanca", "description": "Nome da vizinhan\u00e7a", "is_in_staging": true, "is_partition": false, "type": "STRING", "mode": "NULLABLE"}, {"name": "id_subdistrito", "description": "Identificador do substrito", "is_in_staging": true, "is_partition": false, "type": "STRING", "mode": "NULLABLE"}, {"name": "nome_subdistrito", "description": "Nome do substrito", "is_in_staging": true, "is_partition": false, "type": "STRING", "mode": "NULLABLE"}, {"name": "id_distrito", "description": "Identificador do distrito", "is_in_staging": true, "is_partition": false, "type": "STRING", "mode": "NULLABLE"}, {"name": "nome_distrito", "description": "Nome do distrito", "is_in_staging": true, "is_partition": false, "type": "STRING", "mode": "NULLABLE"}, {"name": "geometria", "description": "Pol\u00edgono do setor censit\u00e1rio", "is_in_staging": true, "is_partition": false, "type": "GEOGRAPHY", "mode": "NULLABLE"}, {"name": "sigla_uf", "description": "Sigla da Unidade da Federa\u00e7\u00e3o", "is_in_staging": true, "is_partition": true, "type": "STRING", "mode": "NULLABLE"}]