[{"name": "id_regiao", "bigquery_type": "STRING", "description": "ID da Regi\u00e3o - IBGE", "temporal_coverage": null, "covered_by_dictionary": false, "directory_column": {"dataset_id": null, "table_id": null, "column_name": null}, "measurement_unit": null, "has_sensitive_data": null, "is_in_staging": null, "is_partition": null, "type": "STRING"}, {"name": "id_uf", "bigquery_type": "STRING", "description": "ID Unidade da Federa\u00e7\u00e3o - IBGE", "temporal_coverage": null, "covered_by_dictionary": false, "directory_column": {"dataset_id": null, "table_id": null, "column_name": null}, "measurement_unit": null, "has_sensitive_data": null, "is_in_staging": null, "is_partition": null, "type": "STRING"}, {"name": "id_domicilio", "bigquery_type": "STRING", "description": "N\u00famero de identifica\u00e7\u00e3o do domic\u00edlio", "temporal_coverage": null, "covered_by_dictionary": false, "directory_column": {"dataset_id": null, "table_id": null, "column_name": null}, "measurement_unit": null, "has_sensitive_data": null, "is_in_staging": null, "is_partition": null, "type": "STRING"}, {"name": "zona_urbana", "bigquery_type": "STRING", "description": "Zona Urbana", "temporal_coverage": null, "covered_by_dictionary": false, "directory_column": {"dataset_id": null, "table_id": null, "column_name": null}, "measurement_unit": null, "has_sensitive_data": null, "is_in_staging": null, "is_partition": null, "type": "STRING"}, {"name": "tipo_zona_domicilio", "bigquery_type": "STRING", "description": "Tipo de zona do domic\u00edlio", "temporal_coverage": null, "covered_by_dictionary": false, "directory_column": {"dataset_id": null, "table_id": null, "column_name": null}, "measurement_unit": null, "has_sensitive_data": null, "is_in_staging": null, "is_partition": null, "type": "STRING"}, {"name": "total_pessoas", "bigquery_type": "INT64", "description": "Total de pessoas", "temporal_coverage": null, "covered_by_dictionary": true, "directory_column": {"dataset_id": null, "table_id": null, "column_name": null}, "measurement_unit": null, "has_sensitive_data": null, "is_in_staging": null, "is_partition": null, "type": "STRING"}, {"name": "total_pessoas_10_mais", "bigquery_type": "INT64", "description": "Total de pessoas 10 anos ou mais", "temporal_coverage": null, "covered_by_dictionary": true, "directory_column": {"dataset_id": null, "table_id": null, "column_name": null}, "measurement_unit": null, "has_sensitive_data": null, "is_in_staging": null, "is_partition": null, "type": "STRING"}, {"name": "especie_domicilio", "bigquery_type": "STRING", "description": "Esp\u00e9cie de domic\u00edlio ", "temporal_coverage": null, "covered_by_dictionary": false, "directory_column": {"dataset_id": null, "table_id": null, "column_name": null}, "measurement_unit": null, "has_sensitive_data": null, "is_in_staging": null, "is_partition": null, "type": "STRING"}, {"name": "tipo_domicilio", "bigquery_type": "STRING", "description": "Tipo de domic\u00edlio", "temporal_coverage": null, "covered_by_dictionary": false, "directory_column": {"dataset_id": null, "table_id": null, "column_name": null}, "measurement_unit": null, "has_sensitive_data": null, "is_in_staging": null, "is_partition": null, "type": "STRING"}, {"name": "tipo_parede", "bigquery_type": "STRING", "description": "Material Predominante das paredes", "temporal_coverage": null, "covered_by_dictionary": false, "directory_column": {"dataset_id": null, "table_id": null, "column_name": null}, "measurement_unit": null, "has_sensitive_data": null, "is_in_staging": null, "is_partition": null, "type": "STRING"}, {"name": "tipo_cobertura", "bigquery_type": "STRING", "description": "Material Predominante no telhado", "temporal_coverage": null, "covered_by_dictionary": false, "directory_column": {"dataset_id": null, "table_id": null, "column_name": null}, "measurement_unit": null, "has_sensitive_data": null, "is_in_staging": null, "is_partition": null, "type": "STRING"}, {"name": "possui_agua_rede", "bigquery_type": "STRING", "description": "\u00c1gua prov\u00e9m de rede?", "temporal_coverage": null, "covered_by_dictionary": false, "directory_column": {"dataset_id": null, "table_id": null, "column_name": null}, "measurement_unit": null, "has_sensitive_data": null, "is_in_staging": null, "is_partition": null, "type": "STRING"}, {"name": "tipo_esgoto", "bigquery_type": "STRING", "description": "Esgotamento sanit\u00e1rio", "temporal_coverage": null, "covered_by_dictionary": false, "directory_column": {"dataset_id": null, "table_id": null, "column_name": null}, "measurement_unit": null, "has_sensitive_data": null, "is_in_staging": null, "is_partition": null, "type": "STRING"}, {"name": "possui_sanitario_exclusivo", "bigquery_type": "STRING", "description": "Sanit\u00e1rio exclusivo do domic\u00edlio?", "temporal_coverage": null, "covered_by_dictionary": false, "directory_column": {"dataset_id": null, "table_id": null, "column_name": null}, "measurement_unit": null, "has_sensitive_data": null, "is_in_staging": null, "is_partition": null, "type": "STRING"}, {"name": "lixo_coletado", "bigquery_type": "STRING", "description": "O lixo \u00e9 coletado?", "temporal_coverage": null, "covered_by_dictionary": false, "directory_column": {"dataset_id": null, "table_id": null, "column_name": null}, "measurement_unit": null, "has_sensitive_data": null, "is_in_staging": null, "is_partition": null, "type": "STRING"}, {"name": "possui_iluminacao_eletrica", "bigquery_type": "STRING", "description": "Possui ilumina\u00e7\u00e3o el\u00e9trica?", "temporal_coverage": null, "covered_by_dictionary": false, "directory_column": {"dataset_id": null, "table_id": null, "column_name": null}, "measurement_unit": null, "has_sensitive_data": null, "is_in_staging": null, "is_partition": null, "type": "STRING"}, {"name": "quantidade_comodos", "bigquery_type": "INT64", "description": "Quantidade de c\u00f4modos", "temporal_coverage": null, "covered_by_dictionary": true, "directory_column": {"dataset_id": null, "table_id": null, "column_name": null}, "measurement_unit": null, "has_sensitive_data": null, "is_in_staging": null, "is_partition": null, "type": "STRING"}, {"name": "quantidade_dormitorios", "bigquery_type": "INT64", "description": "Quantidade de c\u00f4modos servindo como dormit\u00f3rio", "temporal_coverage": null, "covered_by_dictionary": true, "directory_column": {"dataset_id": null, "table_id": null, "column_name": null}, "measurement_unit": null, "has_sensitive_data": null, "is_in_staging": null, "is_partition": null, "type": "STRING"}, {"name": "possui_sanitario", "bigquery_type": "STRING", "description": "Possui sanit\u00e1rio?", "temporal_coverage": null, "covered_by_dictionary": false, "directory_column": {"dataset_id": null, "table_id": null, "column_name": null}, "measurement_unit": null, "has_sensitive_data": null, "is_in_staging": null, "is_partition": null, "type": "STRING"}, {"name": "posse_domocilio", "bigquery_type": "STRING", "description": "Posse do domic\u00edlio", "temporal_coverage": null, "covered_by_dictionary": false, "directory_column": {"dataset_id": null, "table_id": null, "column_name": null}, "measurement_unit": null, "has_sensitive_data": null, "is_in_staging": null, "is_partition": null, "type": "STRING"}, {"name": "possui_filtro", "bigquery_type": "STRING", "description": "Possui filtro?", "temporal_coverage": null, "covered_by_dictionary": false, "directory_column": {"dataset_id": null, "table_id": null, "column_name": null}, "measurement_unit": null, "has_sensitive_data": null, "is_in_staging": null, "is_partition": null, "type": "STRING"}, {"name": "possui_fogao", "bigquery_type": "STRING", "description": "Possui fog\u00e3o?", "temporal_coverage": null, "covered_by_dictionary": false, "directory_column": {"dataset_id": null, "table_id": null, "column_name": null}, "measurement_unit": null, "has_sensitive_data": null, "is_in_staging": null, "is_partition": null, "type": "STRING"}, {"name": "possui_geladeira", "bigquery_type": "STRING", "description": "Possui geladeira?", "temporal_coverage": null, "covered_by_dictionary": false, "directory_column": {"dataset_id": null, "table_id": null, "column_name": null}, "measurement_unit": null, "has_sensitive_data": null, "is_in_staging": null, "is_partition": null, "type": "STRING"}, {"name": "possui_radio", "bigquery_type": "STRING", "description": "Possui r\u00e1dio?", "temporal_coverage": null, "covered_by_dictionary": false, "directory_column": {"dataset_id": null, "table_id": null, "column_name": null}, "measurement_unit": null, "has_sensitive_data": null, "is_in_staging": null, "is_partition": null, "type": "STRING"}, {"name": "possui_tv", "bigquery_type": "STRING", "description": "Possui televis\u00e3o?", "temporal_coverage": null, "covered_by_dictionary": false, "directory_column": {"dataset_id": null, "table_id": null, "column_name": null}, "measurement_unit": null, "has_sensitive_data": null, "is_in_staging": null, "is_partition": null, "type": "STRING"}, {"name": "renda_mensal_domiciliar", "bigquery_type": "FLOAT64", "description": "Renda mensal domiciliar", "temporal_coverage": null, "covered_by_dictionary": true, "directory_column": {"dataset_id": null, "table_id": null, "column_name": null}, "measurement_unit": null, "has_sensitive_data": null, "is_in_staging": null, "is_partition": null, "type": "STRING"}, {"name": "renda_mensal_domiciliar_compativel_1992", "bigquery_type": "FLOAT64", "description": "Renda mensal domiciliar compat\u00edvel com 1992", "temporal_coverage": null, "covered_by_dictionary": true, "directory_column": {"dataset_id": null, "table_id": null, "column_name": null}, "measurement_unit": null, "has_sensitive_data": null, "is_in_staging": null, "is_partition": null, "type": "STRING"}, {"name": "peso_amostral", "bigquery_type": "FLOAT64", "description": "Peso do domic\u00edlio", "temporal_coverage": null, "covered_by_dictionary": true, "directory_column": {"dataset_id": null, "table_id": null, "column_name": null}, "measurement_unit": null, "has_sensitive_data": null, "is_in_staging": null, "is_partition": null, "type": "STRING"}, {"name": "valor_aluguel_pago", "bigquery_type": "FLOAT64", "description": "Valor do aluguel", "temporal_coverage": null, "covered_by_dictionary": true, "directory_column": {"dataset_id": null, "table_id": null, "column_name": null}, "measurement_unit": null, "has_sensitive_data": null, "is_in_staging": null, "is_partition": null, "type": "STRING"}, {"name": "prestacao", "bigquery_type": "FLOAT64", "description": "Valor da presta\u00e7\u00e3o", "temporal_coverage": null, "covered_by_dictionary": true, "directory_column": {"dataset_id": null, "table_id": null, "column_name": null}, "measurement_unit": null, "has_sensitive_data": null, "is_in_staging": null, "is_partition": null, "type": "STRING"}, {"name": "deflator", "bigquery_type": "INT64", "description": "Deflator (base outubro de 2012)", "temporal_coverage": null, "covered_by_dictionary": true, "directory_column": {"dataset_id": null, "table_id": null, "column_name": null}, "measurement_unit": null, "has_sensitive_data": null, "is_in_staging": null, "is_partition": null, "type": "STRING"}, {"name": "conversor_moeda", "bigquery_type": "INT64", "description": "Conversor de Moeda", "temporal_coverage": null, "covered_by_dictionary": true, "directory_column": {"dataset_id": null, "table_id": null, "column_name": null}, "measurement_unit": null, "has_sensitive_data": null, "is_in_staging": null, "is_partition": null, "type": "STRING"}, {"name": "renda_domicilio_deflacionada", "bigquery_type": "FLOAT64", "description": "Renda do domic\u00edlio - Valor deflacionado", "temporal_coverage": null, "covered_by_dictionary": true, "directory_column": {"dataset_id": null, "table_id": null, "column_name": null}, "measurement_unit": null, "has_sensitive_data": null, "is_in_staging": null, "is_partition": null, "type": "STRING"}, {"name": "renda_mensal_domiciliar_compativel_1992_deflacionada", "bigquery_type": "FLOAT64", "description": "Renda mensal domiciliar compat\u00edvel com 1992 - Valor deflacionado", "temporal_coverage": null, "covered_by_dictionary": true, "directory_column": {"dataset_id": null, "table_id": null, "column_name": null}, "measurement_unit": null, "has_sensitive_data": null, "is_in_staging": null, "is_partition": null, "type": "STRING"}, {"name": "aluguel_deflacionado", "bigquery_type": "FLOAT64", "description": "Aluguel - Valor deflacionado ", "temporal_coverage": null, "covered_by_dictionary": true, "directory_column": {"dataset_id": null, "table_id": null, "column_name": null}, "measurement_unit": null, "has_sensitive_data": null, "is_in_staging": null, "is_partition": null, "type": "STRING"}, {"name": "prestacao_deflacionado", "bigquery_type": "FLOAT64", "description": "Presta\u00e7\u00e3o - Valor deflacionado", "temporal_coverage": null, "covered_by_dictionary": true, "directory_column": {"dataset_id": null, "table_id": null, "column_name": null}, "measurement_unit": null, "has_sensitive_data": null, "is_in_staging": null, "is_partition": null, "type": "STRING"}, {"name": "numero_familia", "bigquery_type": "INT64", "description": "N\u00famero da fam\u00edlia", "temporal_coverage": null, "covered_by_dictionary": true, "directory_column": {"dataset_id": null, "table_id": null, "column_name": null}, "measurement_unit": null, "has_sensitive_data": null, "is_in_staging": null, "is_partition": null, "type": "STRING"}, {"name": "id_regiao_metropolitana", "bigquery_type": "STRING", "description": "ID da Regi\u00e3o Metropolitana", "temporal_coverage": null, "covered_by_dictionary": false, "directory_column": {"dataset_id": null, "table_id": null, "column_name": null}, "measurement_unit": null, "has_sensitive_data": null, "is_in_staging": null, "is_partition": null, "type": "STRING"}, {"name": "sexo", "bigquery_type": "STRING", "description": "Sexo", "temporal_coverage": null, "covered_by_dictionary": false, "directory_column": {"dataset_id": null, "table_id": null, "column_name": null}, "measurement_unit": null, "has_sensitive_data": null, "is_in_staging": null, "is_partition": null, "type": "STRING"}, {"name": "condicao_domicilio", "bigquery_type": "STRING", "description": "Condi\u00e7\u00e3o no domic\u00edlio", "temporal_coverage": null, "covered_by_dictionary": false, "directory_column": {"dataset_id": null, "table_id": null, "column_name": null}, "measurement_unit": null, "has_sensitive_data": null, "is_in_staging": null, "is_partition": null, "type": "STRING"}, {"name": "condicao_familia", "bigquery_type": "STRING", "description": "Condi\u00e7\u00e3o na fam\u00edlia", "temporal_coverage": null, "covered_by_dictionary": false, "directory_column": {"dataset_id": null, "table_id": null, "column_name": null}, "measurement_unit": null, "has_sensitive_data": null, "is_in_staging": null, "is_partition": null, "type": "STRING"}, {"name": "dia_nascimento", "bigquery_type": "INT64", "description": "Dia do nascimento", "temporal_coverage": null, "covered_by_dictionary": true, "directory_column": {"dataset_id": null, "table_id": null, "column_name": null}, "measurement_unit": null, "has_sensitive_data": null, "is_in_staging": null, "is_partition": null, "type": "STRING"}, {"name": "mes_nascimento", "bigquery_type": "INT64", "description": "M\u00eas do nascimento", "temporal_coverage": null, "covered_by_dictionary": false, "directory_column": {"dataset_id": null, "table_id": null, "column_name": null}, "measurement_unit": "m\u00eas", "has_sensitive_data": null, "is_in_staging": null, "is_partition": null, "type": "STRING"}, {"name": "ano_nascimento", "bigquery_type": "INT64", "description": "Ano do nascimento", "temporal_coverage": null, "covered_by_dictionary": true, "directory_column": {"dataset_id": null, "table_id": null, "column_name": null}, "measurement_unit": "ano", "has_sensitive_data": null, "is_in_staging": null, "is_partition": null, "type": "STRING"}, {"name": "idade", "bigquery_type": "INT64", "description": "Idade", "temporal_coverage": null, "covered_by_dictionary": true, "directory_column": {"dataset_id": null, "table_id": null, "column_name": null}, "measurement_unit": null, "has_sensitive_data": null, "is_in_staging": null, "is_partition": null, "type": "STRING"}, {"name": "sabe_ler_escrever", "bigquery_type": "STRING", "description": "Sabe ler e escrever?", "temporal_coverage": null, "covered_by_dictionary": false, "directory_column": {"dataset_id": null, "table_id": null, "column_name": null}, "measurement_unit": null, "has_sensitive_data": null, "is_in_staging": null, "is_partition": null, "type": "STRING"}, {"name": "serie_frequentada", "bigquery_type": "STRING", "description": "S\u00e9rie que frequenta", "temporal_coverage": null, "covered_by_dictionary": false, "directory_column": {"dataset_id": null, "table_id": null, "column_name": null}, "measurement_unit": null, "has_sensitive_data": null, "is_in_staging": null, "is_partition": null, "type": "STRING"}, {"name": "grau_frequentada", "bigquery_type": "STRING", "description": "Grau que frequenta ", "temporal_coverage": null, "covered_by_dictionary": false, "directory_column": {"dataset_id": null, "table_id": null, "column_name": null}, "measurement_unit": null, "has_sensitive_data": null, "is_in_staging": null, "is_partition": null, "type": "STRING"}, {"name": "ultima_seria_frequentada", "bigquery_type": "INT64", "description": "\u00daltima s\u00e9rie frequentada (para quem n\u00e3o frequenta escola)", "temporal_coverage": null, "covered_by_dictionary": true, "directory_column": {"dataset_id": null, "table_id": null, "column_name": null}, "measurement_unit": null, "has_sensitive_data": null, "is_in_staging": null, "is_partition": null, "type": "STRING"}, {"name": "ultimo_grau_frequentado", "bigquery_type": "STRING", "description": "\u00daltimo grau frequentado (para quem n\u00e3o frequenta escola)", "temporal_coverage": null, "covered_by_dictionary": false, "directory_column": {"dataset_id": null, "table_id": null, "column_name": null}, "measurement_unit": null, "has_sensitive_data": null, "is_in_staging": null, "is_partition": null, "type": "STRING"}, {"name": "tinha_outro_trabalho", "bigquery_type": "STRING", "description": "Tinha outro trabalho na semana de refer\u00eancia", "temporal_coverage": null, "covered_by_dictionary": false, "directory_column": {"dataset_id": null, "table_id": null, "column_name": null}, "measurement_unit": null, "has_sensitive_data": null, "is_in_staging": null, "is_partition": null, "type": "STRING"}, {"name": "ocupacao_semana", "bigquery_type": "INT64", "description": "Ocupa\u00e7\u00e3o na semana", "temporal_coverage": null, "covered_by_dictionary": true, "directory_column": {"dataset_id": "cbo", "table_id": "cbo", "column_name": "cbo"}, "measurement_unit": null, "has_sensitive_data": null, "is_in_staging": null, "is_partition": null, "type": "STRING"}, {"name": "atividade_ramo_negocio_semana", "bigquery_type": "INT64", "description": "Atividade ou ramo do n\u00e9gocio na semana", "temporal_coverage": null, "covered_by_dictionary": true, "directory_column": {"dataset_id": "cbo", "table_id": "cbo", "column_name": "cbo"}, "measurement_unit": null, "has_sensitive_data": null, "is_in_staging": null, "is_partition": null, "type": "STRING"}, {"name": "possui_carteira_assinada", "bigquery_type": "STRING", "description": "Tem carteira de trabalho assinada", "temporal_coverage": null, "covered_by_dictionary": false, "directory_column": {"dataset_id": null, "table_id": null, "column_name": null}, "measurement_unit": null, "has_sensitive_data": null, "is_in_staging": null, "is_partition": null, "type": "STRING"}, {"name": "rendimento_mensal_dinheiro", "bigquery_type": "FLOAT64", "description": "Rendimento mensal em dinheiro", "temporal_coverage": null, "covered_by_dictionary": false, "directory_column": {"dataset_id": null, "table_id": null, "column_name": null}, "measurement_unit": null, "has_sensitive_data": null, "is_in_staging": null, "is_partition": null, "type": "STRING"}, {"name": "rendimento_mensal_produto_mercadoria", "bigquery_type": "FLOAT64", "description": "Rendimento mensal em produtos ou mercadorias", "temporal_coverage": null, "covered_by_dictionary": false, "directory_column": {"dataset_id": null, "table_id": null, "column_name": null}, "measurement_unit": null, "has_sensitive_data": null, "is_in_staging": null, "is_partition": null, "type": "STRING"}, {"name": "horas_trabalhadas_semana", "bigquery_type": "INT64", "description": "Horas normalmente trabalhadas na semana - Ocupa\u00e7\u00e3o principal", "temporal_coverage": null, "covered_by_dictionary": false, "directory_column": {"dataset_id": null, "table_id": null, "column_name": null}, "measurement_unit": "h", "has_sensitive_data": null, "is_in_staging": null, "is_partition": null, "type": "STRING"}, {"name": "rendimento_mensal_dinheiro_outra", "bigquery_type": "FLOAT64", "description": "Rendimento em mensal dinheiro Outra", "temporal_coverage": null, "covered_by_dictionary": true, "directory_column": {"dataset_id": null, "table_id": null, "column_name": null}, "measurement_unit": null, "has_sensitive_data": null, "is_in_staging": null, "is_partition": null, "type": "STRING"}, {"name": "rendimento_mensal_produto_outra", "bigquery_type": "FLOAT64", "description": "Rendimento mensal em produtos ou mercadorias outras", "temporal_coverage": null, "covered_by_dictionary": true, "directory_column": {"dataset_id": null, "table_id": null, "column_name": null}, "measurement_unit": null, "has_sensitive_data": null, "is_in_staging": null, "is_partition": null, "type": "STRING"}, {"name": "horas_trabalhadas_outros_trabalhos", "bigquery_type": "INT64", "description": "Horas normalmente trabalhadas na semana - Outros trabalhos", "temporal_coverage": null, "covered_by_dictionary": false, "directory_column": {"dataset_id": null, "table_id": null, "column_name": null}, "measurement_unit": "h", "has_sensitive_data": null, "is_in_staging": null, "is_partition": null, "type": "STRING"}, {"name": "contribui_previdencia", "bigquery_type": "STRING", "description": "Contribui para instituto de previd\u00eancia", "temporal_coverage": null, "covered_by_dictionary": false, "directory_column": {"dataset_id": null, "table_id": null, "column_name": null}, "measurement_unit": null, "has_sensitive_data": null, "is_in_staging": null, "is_partition": null, "type": "STRING"}, {"name": "tipo_instituto_previdencia", "bigquery_type": "STRING", "description": "Tipo de instituto de previd\u00eancia", "temporal_coverage": null, "covered_by_dictionary": false, "directory_column": {"dataset_id": null, "table_id": null, "column_name": null}, "measurement_unit": null, "has_sensitive_data": null, "is_in_staging": null, "is_partition": null, "type": "STRING"}, {"name": "tomou_providencia_conseguir_trabalho_semana", "bigquery_type": null, "description": null, "temporal_coverage": null, "covered_by_dictionary": null, "directory_column": {"dataset_id": null, "table_id": null, "column_name": null}, "measurement_unit": null, "has_sensitive_data": null, "is_in_staging": null, "is_partition": null, "type": "STRING"}, {"name": "tomou_providencia_ultimos_2_meses", "bigquery_type": null, "description": null, "temporal_coverage": null, "covered_by_dictionary": null, "directory_column": {"dataset_id": null, "table_id": null, "column_name": null}, "measurement_unit": null, "has_sensitive_data": null, "is_in_staging": null, "is_partition": null, "type": "STRING"}, {"name": "qual_medida", "bigquery_type": "STRING", "description": "O que foi tomado de medida para encontrar um emprego", "temporal_coverage": null, "covered_by_dictionary": false, "directory_column": {"dataset_id": null, "table_id": null, "column_name": null}, "measurement_unit": null, "has_sensitive_data": null, "is_in_staging": null, "is_partition": null, "type": "STRING"}, {"name": "tinha_carteira_assinada_ultimo_emprego", "bigquery_type": null, "description": null, "temporal_coverage": null, "covered_by_dictionary": null, "directory_column": {"dataset_id": null, "table_id": null, "column_name": null}, "measurement_unit": null, "has_sensitive_data": null, "is_in_staging": null, "is_partition": null, "type": "STRING"}, {"name": "valor_aposentadoria", "bigquery_type": "FLOAT64", "description": "Valor da Aposentadoria", "temporal_coverage": null, "covered_by_dictionary": true, "directory_column": {"dataset_id": null, "table_id": null, "column_name": null}, "measurement_unit": null, "has_sensitive_data": null, "is_in_staging": null, "is_partition": null, "type": "STRING"}, {"name": "valor_pensao", "bigquery_type": "FLOAT64", "description": "Valor da Pens\u00e3o", "temporal_coverage": null, "covered_by_dictionary": true, "directory_column": {"dataset_id": null, "table_id": null, "column_name": null}, "measurement_unit": null, "has_sensitive_data": null, "is_in_staging": null, "is_partition": null, "type": "STRING"}, {"name": "valor_abono_permanente", "bigquery_type": "FLOAT64", "description": "Valor do b\u00f4nus do sal\u00e1rio permanente", "temporal_coverage": null, "covered_by_dictionary": true, "directory_column": {"dataset_id": null, "table_id": null, "column_name": null}, "measurement_unit": null, "has_sensitive_data": null, "is_in_staging": null, "is_partition": null, "type": "STRING"}, {"name": "valor_aluguel", "bigquery_type": "FLOAT64", "description": "Valor do Aluguel recebido", "temporal_coverage": null, "covered_by_dictionary": true, "directory_column": {"dataset_id": null, "table_id": null, "column_name": null}, "measurement_unit": null, "has_sensitive_data": null, "is_in_staging": null, "is_partition": null, "type": "STRING"}, {"name": "renda_outras", "bigquery_type": "FLOAT64", "description": "Valor de outras rendas", "temporal_coverage": null, "covered_by_dictionary": true, "directory_column": {"dataset_id": null, "table_id": null, "column_name": null}, "measurement_unit": null, "has_sensitive_data": null, "is_in_staging": null, "is_partition": null, "type": "STRING"}, {"name": "rendimento_mensal_ocupacao_principal", "bigquery_type": "FLOAT64", "description": "Rendimento mensal ocupa\u00e7\u00e3o principal", "temporal_coverage": null, "covered_by_dictionary": true, "directory_column": {"dataset_id": null, "table_id": null, "column_name": null}, "measurement_unit": null, "has_sensitive_data": null, "is_in_staging": null, "is_partition": null, "type": "STRING"}, {"name": "rendimento_mensal_todos_trabalhos", "bigquery_type": "FLOAT64", "description": "Rendimento mensal todos trabalhos", "temporal_coverage": null, "covered_by_dictionary": true, "directory_column": {"dataset_id": null, "table_id": null, "column_name": null}, "measurement_unit": null, "has_sensitive_data": null, "is_in_staging": null, "is_partition": null, "type": "STRING"}, {"name": "rendimento_mensal_todas_fontes", "bigquery_type": "FLOAT64", "description": "Rendimento mensal todas fontes", "temporal_coverage": null, "covered_by_dictionary": true, "directory_column": {"dataset_id": null, "table_id": null, "column_name": null}, "measurement_unit": null, "has_sensitive_data": null, "is_in_staging": null, "is_partition": null, "type": "STRING"}, {"name": "atividade_ramo_negocio_agregado", "bigquery_type": "STRING", "description": "Atividade ou ramo do n\u00e9gocio na semana - Agregado", "temporal_coverage": null, "covered_by_dictionary": false, "directory_column": {"dataset_id": null, "table_id": null, "column_name": null}, "measurement_unit": null, "has_sensitive_data": null, "is_in_staging": null, "is_partition": null, "type": "STRING"}, {"name": "horas_trabalhadas_todos_trabalhos", "bigquery_type": "INT64", "description": "Horas normalmente trabalhadas na semana em todos os trabalhos", "temporal_coverage": null, "covered_by_dictionary": false, "directory_column": {"dataset_id": null, "table_id": null, "column_name": null}, "measurement_unit": "h", "has_sensitive_data": null, "is_in_staging": null, "is_partition": null, "type": "STRING"}, {"name": "posicao_ocupacao", "bigquery_type": null, "description": null, "temporal_coverage": null, "covered_by_dictionary": null, "directory_column": {"dataset_id": null, "table_id": null, "column_name": null}, "measurement_unit": null, "has_sensitive_data": null, "is_in_staging": null, "is_partition": null, "type": "STRING"}, {"name": "grupos_ocupacao", "bigquery_type": "STRING", "description": "Grupos de ocupa\u00e7\u00e3o na semana", "temporal_coverage": null, "covered_by_dictionary": false, "directory_column": {"dataset_id": null, "table_id": null, "column_name": null}, "measurement_unit": null, "has_sensitive_data": null, "is_in_staging": null, "is_partition": null, "type": "STRING"}, {"name": "numero_membros_familia", "bigquery_type": null, "description": null, "temporal_coverage": null, "covered_by_dictionary": null, "directory_column": {"dataset_id": null, "table_id": null, "column_name": null}, "measurement_unit": null, "has_sensitive_data": null, "is_in_staging": null, "is_partition": null, "type": "STRING"}, {"name": "rendimento_mensal_familia", "bigquery_type": null, "description": null, "temporal_coverage": null, "covered_by_dictionary": null, "directory_column": {"dataset_id": null, "table_id": null, "column_name": null}, "measurement_unit": null, "has_sensitive_data": null, "is_in_staging": null, "is_partition": null, "type": "STRING"}, {"name": "ordem", "bigquery_type": "INT64", "description": "N\u00famero de ordem da pessoa", "temporal_coverage": null, "covered_by_dictionary": false, "directory_column": {"dataset_id": null, "table_id": null, "column_name": null}, "measurement_unit": null, "has_sensitive_data": null, "is_in_staging": null, "is_partition": null, "type": "STRING"}, {"name": "raca_cor", "bigquery_type": "STRING", "description": "Ra\u00e7a ou Cor (autodeclara\u00e7\u00e3o)", "temporal_coverage": null, "covered_by_dictionary": false, "directory_column": {"dataset_id": null, "table_id": null, "column_name": null}, "measurement_unit": null, "has_sensitive_data": null, "is_in_staging": null, "is_partition": null, "type": "STRING"}, {"name": "anos_estudo", "bigquery_type": "INT64", "description": "Anos de estudo", "temporal_coverage": null, "covered_by_dictionary": true, "directory_column": {"dataset_id": null, "table_id": null, "column_name": null}, "measurement_unit": "ano", "has_sensitive_data": null, "is_in_staging": null, "is_partition": null, "type": "STRING"}, {"name": "frequenta_escola", "bigquery_type": "STRING", "description": "Frequenta a escola?", "temporal_coverage": null, "covered_by_dictionary": false, "directory_column": {"dataset_id": null, "table_id": null, "column_name": null}, "measurement_unit": null, "has_sensitive_data": null, "is_in_staging": null, "is_partition": null, "type": "STRING"}, {"name": "trabalhou_semana", "bigquery_type": "STRING", "description": "Trabalhou na semana", "temporal_coverage": null, "covered_by_dictionary": false, "directory_column": {"dataset_id": null, "table_id": null, "column_name": null}, "measurement_unit": null, "has_sensitive_data": null, "is_in_staging": null, "is_partition": null, "type": "STRING"}, {"name": "tinha_trabalhado_semana", "bigquery_type": "STRING", "description": "Tinha trabalhado na semana?", "temporal_coverage": null, "covered_by_dictionary": false, "directory_column": {"dataset_id": null, "table_id": null, "column_name": null}, "measurement_unit": null, "has_sensitive_data": null, "is_in_staging": null, "is_partition": null, "type": "STRING"}, {"name": "ocupacao_ano_anterior", "bigquery_type": "INT64", "description": "Ocupa\u00e7\u00e3o no ano anterior", "temporal_coverage": null, "covered_by_dictionary": false, "directory_column": {"dataset_id": null, "table_id": null, "column_name": null}, "measurement_unit": null, "has_sensitive_data": null, "is_in_staging": null, "is_partition": null, "type": "STRING"}, {"name": "atividade_ramo_negocio_anterior", "bigquery_type": "INT64", "description": "Atividade ou ramo do neg\u00f3cio anterior", "temporal_coverage": null, "covered_by_dictionary": false, "directory_column": {"dataset_id": null, "table_id": null, "column_name": null}, "measurement_unit": null, "has_sensitive_data": null, "is_in_staging": null, "is_partition": null, "type": "STRING"}, {"name": "rendimento_mensal_dinheiro_deflacionado", "bigquery_type": "FLOAT64", "description": "Rendimento mensal em dinheiro - Valor deflacionado", "temporal_coverage": null, "covered_by_dictionary": false, "directory_column": {"dataset_id": null, "table_id": null, "column_name": null}, "measurement_unit": null, "has_sensitive_data": null, "is_in_staging": null, "is_partition": null, "type": "STRING"}, {"name": "rendimento_mensal_produto_mercadoria_deflacionado", "bigquery_type": "FLOAT64", "description": "Rendimento mensal em produto ou mercadoria - Valor deflacionado", "temporal_coverage": null, "covered_by_dictionary": false, "directory_column": {"dataset_id": null, "table_id": null, "column_name": null}, "measurement_unit": null, "has_sensitive_data": null, "is_in_staging": null, "is_partition": null, "type": "STRING"}, {"name": "rendimento_mensal_dinheiro_outra_deflacionado", "bigquery_type": "FLOAT64", "description": "Rendimento mensal em dinheiro outra - Valor deflacionado", "temporal_coverage": null, "covered_by_dictionary": false, "directory_column": {"dataset_id": null, "table_id": null, "column_name": null}, "measurement_unit": null, "has_sensitive_data": null, "is_in_staging": null, "is_partition": null, "type": "STRING"}, {"name": "rendimento_mensal_produto_mercadoria_outra_deflacionado", "bigquery_type": null, "description": null, "temporal_coverage": null, "covered_by_dictionary": null, "directory_column": {"dataset_id": null, "table_id": null, "column_name": null}, "measurement_unit": null, "has_sensitive_data": null, "is_in_staging": null, "is_partition": null, "type": "STRING"}, {"name": "rendimento_mensal_ocupacao_principal_deflacionado", "bigquery_type": "FLOAT64", "description": "Rendimento mensal da ocupa\u00e7\u00e3o principal - Valor deflacionado", "temporal_coverage": null, "covered_by_dictionary": false, "directory_column": {"dataset_id": null, "table_id": null, "column_name": null}, "measurement_unit": null, "has_sensitive_data": null, "is_in_staging": null, "is_partition": null, "type": "STRING"}, {"name": "rendimento_mensal_todos_trabalhos_deflacionado", "bigquery_type": "FLOAT64", "description": "Rendimento mensal de todos os trabalhos - Valor deflacionado", "temporal_coverage": null, "covered_by_dictionary": false, "directory_column": {"dataset_id": null, "table_id": null, "column_name": null}, "measurement_unit": null, "has_sensitive_data": null, "is_in_staging": null, "is_partition": null, "type": "STRING"}, {"name": "rendimento_mensal_todas_fontes_deflacionado", "bigquery_type": "FLOAT64", "description": "Rendimento mensal de todas as fontes - Valor deflacionado", "temporal_coverage": null, "covered_by_dictionary": false, "directory_column": {"dataset_id": null, "table_id": null, "column_name": null}, "measurement_unit": null, "has_sensitive_data": null, "is_in_staging": null, "is_partition": null, "type": "STRING"}, {"name": "rendimento_mensal_familia_deflacionado", "bigquery_type": "FLOAT64", "description": "Rendimento mensal da fam\u00edlia - Valor deflacionado", "temporal_coverage": null, "covered_by_dictionary": false, "directory_column": {"dataset_id": null, "table_id": null, "column_name": null}, "measurement_unit": null, "has_sensitive_data": null, "is_in_staging": null, "is_partition": null, "type": "STRING"}, {"name": "valor_aposentadoria_deflacionado", "bigquery_type": "FLOAT64", "description": "Valor da aposentadoria - Valor deflacionado", "temporal_coverage": null, "covered_by_dictionary": false, "directory_column": {"dataset_id": null, "table_id": null, "column_name": null}, "measurement_unit": null, "has_sensitive_data": null, "is_in_staging": null, "is_partition": null, "type": "STRING"}, {"name": "valor_pensao_deflacionado", "bigquery_type": "FLOAT64", "description": "Valor da Pens\u00e3o - Valor deflacionado", "temporal_coverage": null, "covered_by_dictionary": false, "directory_column": {"dataset_id": null, "table_id": null, "column_name": null}, "measurement_unit": null, "has_sensitive_data": null, "is_in_staging": null, "is_partition": null, "type": "STRING"}, {"name": "valor_abono_deflacionado", "bigquery_type": "FLOAT64", "description": "Valor do abono - Valor deflacionado", "temporal_coverage": null, "covered_by_dictionary": false, "directory_column": {"dataset_id": null, "table_id": null, "column_name": null}, "measurement_unit": null, "has_sensitive_data": null, "is_in_staging": null, "is_partition": null, "type": "STRING"}, {"name": "valor_aluguel_deflacionado", "bigquery_type": "FLOAT64", "description": "Valor do Aluguel - Valor deflacionado", "temporal_coverage": null, "covered_by_dictionary": false, "directory_column": {"dataset_id": null, "table_id": null, "column_name": null}, "measurement_unit": null, "has_sensitive_data": null, "is_in_staging": null, "is_partition": null, "type": "STRING"}, {"name": "rendas_outras_deflacionado", "bigquery_type": "FLOAT64", "description": "Rendas Outras - Valor deflacionado", "temporal_coverage": null, "covered_by_dictionary": false, "directory_column": {"dataset_id": null, "table_id": null, "column_name": null}, "measurement_unit": null, "has_sensitive_data": null, "is_in_staging": null, "is_partition": null, "type": "STRING"}]