[{"name": "ano", "bigquery_type": null, "description": null, "temporal_coverage": null, "covered_by_dictionary": null, "directory_column": {"dataset_id": null, "table_id": null, "column_name": null}, "measurement_unit": null, "has_sensitive_data": null, "observations": null, "is_in_staging": null, "is_partition": null, "type": "STRING"}, {"name": "mes", "bigquery_type": null, "description": null, "temporal_coverage": null, "covered_by_dictionary": null, "directory_column": {"dataset_id": null, "table_id": null, "column_name": null}, "measurement_unit": null, "has_sensitive_data": null, "observations": null, "is_in_staging": null, "is_partition": null, "type": "STRING"}, {"name": "taxa_homicidio_doloso", "bigquery_type": null, "description": null, "temporal_coverage": null, "covered_by_dictionary": null, "directory_column": {"dataset_id": null, "table_id": null, "column_name": null}, "measurement_unit": null, "has_sensitive_data": null, "observations": null, "is_in_staging": null, "is_partition": null, "type": "STRING"}, {"name": "taxa_latrocinio", "bigquery_type": null, "description": null, "temporal_coverage": null, "covered_by_dictionary": null, "directory_column": {"dataset_id": null, "table_id": null, "column_name": null}, "measurement_unit": null, "has_sensitive_data": null, "observations": null, "is_in_staging": null, "is_partition": null, "type": "STRING"}, {"name": "taxa_lesao_corporal_morte", "bigquery_type": null, "description": null, "temporal_coverage": null, "covered_by_dictionary": null, "directory_column": {"dataset_id": null, "table_id": null, "column_name": null}, "measurement_unit": null, "has_sensitive_data": null, "observations": null, "is_in_staging": null, "is_partition": null, "type": "STRING"}, {"name": "taxa_crimes_violentos_letais_intencionais", "bigquery_type": null, "description": null, "temporal_coverage": null, "covered_by_dictionary": null, "directory_column": {"dataset_id": null, "table_id": null, "column_name": null}, "measurement_unit": null, "has_sensitive_data": null, "observations": null, "is_in_staging": null, "is_partition": null, "type": "STRING"}, {"name": "taxa_homicidio_intervencao_policial", "bigquery_type": null, "description": null, "temporal_coverage": null, "covered_by_dictionary": null, "directory_column": {"dataset_id": null, "table_id": null, "column_name": null}, "measurement_unit": null, "has_sensitive_data": null, "observations": null, "is_in_staging": null, "is_partition": null, "type": "STRING"}, {"name": "taxa_letalidade_violenta", "bigquery_type": null, "description": null, "temporal_coverage": null, "covered_by_dictionary": null, "directory_column": {"dataset_id": null, "table_id": null, "column_name": null}, "measurement_unit": null, "has_sensitive_data": null, "observations": null, "is_in_staging": null, "is_partition": null, "type": "STRING"}, {"name": "taxa_tentativa_homicidio", "bigquery_type": null, "description": null, "temporal_coverage": null, "covered_by_dictionary": null, "directory_column": {"dataset_id": null, "table_id": null, "column_name": null}, "measurement_unit": null, "has_sensitive_data": null, "observations": null, "is_in_staging": null, "is_partition": null, "type": "STRING"}, {"name": "taxa_lesao_corporal_dolosa", "bigquery_type": null, "description": null, "temporal_coverage": null, "covered_by_dictionary": null, "directory_column": {"dataset_id": null, "table_id": null, "column_name": null}, "measurement_unit": null, "has_sensitive_data": null, "observations": null, "is_in_staging": null, "is_partition": null, "type": "STRING"}, {"name": "taxa_estupro", "bigquery_type": null, "description": null, "temporal_coverage": null, "covered_by_dictionary": null, "directory_column": {"dataset_id": null, "table_id": null, "column_name": null}, "measurement_unit": null, "has_sensitive_data": null, "observations": null, "is_in_staging": null, "is_partition": null, "type": "STRING"}, {"name": "taxa_homicidio_culposo", "bigquery_type": null, "description": null, "temporal_coverage": null, "covered_by_dictionary": null, "directory_column": {"dataset_id": null, "table_id": null, "column_name": null}, "measurement_unit": null, "has_sensitive_data": null, "observations": null, "is_in_staging": null, "is_partition": null, "type": "STRING"}, {"name": "taxa_lesao_corporal_culposa", "bigquery_type": null, "description": null, "temporal_coverage": null, "covered_by_dictionary": null, "directory_column": {"dataset_id": null, "table_id": null, "column_name": null}, "measurement_unit": null, "has_sensitive_data": null, "observations": null, "is_in_staging": null, "is_partition": null, "type": "STRING"}, {"name": "taxa_roubo_transeunte", "bigquery_type": null, "description": null, "temporal_coverage": null, "covered_by_dictionary": null, "directory_column": {"dataset_id": null, "table_id": null, "column_name": null}, "measurement_unit": null, "has_sensitive_data": null, "observations": null, "is_in_staging": null, "is_partition": null, "type": "STRING"}, {"name": "taxa_roubo_celular", "bigquery_type": null, "description": null, "temporal_coverage": null, "covered_by_dictionary": null, "directory_column": {"dataset_id": null, "table_id": null, "column_name": null}, "measurement_unit": null, "has_sensitive_data": null, "observations": null, "is_in_staging": null, "is_partition": null, "type": "STRING"}, {"name": "taxa_roubo_corporal_coletivo", "bigquery_type": null, "description": null, "temporal_coverage": null, "covered_by_dictionary": null, "directory_column": {"dataset_id": null, "table_id": null, "column_name": null}, "measurement_unit": null, "has_sensitive_data": null, "observations": null, "is_in_staging": null, "is_partition": null, "type": "STRING"}, {"name": "taxa_roubo_rua", "bigquery_type": null, "description": null, "temporal_coverage": null, "covered_by_dictionary": null, "directory_column": {"dataset_id": null, "table_id": null, "column_name": null}, "measurement_unit": null, "has_sensitive_data": null, "observations": null, "is_in_staging": null, "is_partition": null, "type": "STRING"}, {"name": "taxa_roubo_veiculo", "bigquery_type": null, "description": null, "temporal_coverage": null, "covered_by_dictionary": null, "directory_column": {"dataset_id": null, "table_id": null, "column_name": null}, "measurement_unit": null, "has_sensitive_data": null, "observations": null, "is_in_staging": null, "is_partition": null, "type": "STRING"}, {"name": "taxa_roubo_carga", "bigquery_type": null, "description": null, "temporal_coverage": null, "covered_by_dictionary": null, "directory_column": {"dataset_id": null, "table_id": null, "column_name": null}, "measurement_unit": null, "has_sensitive_data": null, "observations": null, "is_in_staging": null, "is_partition": null, "type": "STRING"}, {"name": "taxa_roubo_comercio", "bigquery_type": null, "description": null, "temporal_coverage": null, "covered_by_dictionary": null, "directory_column": {"dataset_id": null, "table_id": null, "column_name": null}, "measurement_unit": null, "has_sensitive_data": null, "observations": null, "is_in_staging": null, "is_partition": null, "type": "STRING"}, {"name": "taxa_roubo_residencia", "bigquery_type": null, "description": null, "temporal_coverage": null, "covered_by_dictionary": null, "directory_column": {"dataset_id": null, "table_id": null, "column_name": null}, "measurement_unit": null, "has_sensitive_data": null, "observations": null, "is_in_staging": null, "is_partition": null, "type": "STRING"}, {"name": "taxa_roubo_banco", "bigquery_type": null, "description": null, "temporal_coverage": null, "covered_by_dictionary": null, "directory_column": {"dataset_id": null, "table_id": null, "column_name": null}, "measurement_unit": null, "has_sensitive_data": null, "observations": null, "is_in_staging": null, "is_partition": null, "type": "STRING"}, {"name": "taxa_roubo_caixa_eletronico", "bigquery_type": null, "description": null, "temporal_coverage": null, "covered_by_dictionary": null, "directory_column": {"dataset_id": null, "table_id": null, "column_name": null}, "measurement_unit": null, "has_sensitive_data": null, "observations": null, "is_in_staging": null, "is_partition": null, "type": "STRING"}, {"name": "taxa_roubo_conducao_saque", "bigquery_type": null, "description": null, "temporal_coverage": null, "covered_by_dictionary": null, "directory_column": {"dataset_id": null, "table_id": null, "column_name": null}, "measurement_unit": null, "has_sensitive_data": null, "observations": null, "is_in_staging": null, "is_partition": null, "type": "STRING"}, {"name": "taxa_roubo_apos_saque", "bigquery_type": null, "description": null, "temporal_coverage": null, "covered_by_dictionary": null, "directory_column": {"dataset_id": null, "table_id": null, "column_name": null}, "measurement_unit": null, "has_sensitive_data": null, "observations": null, "is_in_staging": null, "is_partition": null, "type": "STRING"}, {"name": "taxa_roubo_bicicleta", "bigquery_type": null, "description": null, "temporal_coverage": null, "covered_by_dictionary": null, "directory_column": {"dataset_id": null, "table_id": null, "column_name": null}, "measurement_unit": null, "has_sensitive_data": null, "observations": null, "is_in_staging": null, "is_partition": null, "type": "STRING"}, {"name": "taxa_outros_roubos", "bigquery_type": null, "description": null, "temporal_coverage": null, "covered_by_dictionary": null, "directory_column": {"dataset_id": null, "table_id": null, "column_name": null}, "measurement_unit": null, "has_sensitive_data": null, "observations": null, "is_in_staging": null, "is_partition": null, "type": "STRING"}, {"name": "taxa_total_roubos", "bigquery_type": null, "description": null, "temporal_coverage": null, "covered_by_dictionary": null, "directory_column": {"dataset_id": null, "table_id": null, "column_name": null}, "measurement_unit": null, "has_sensitive_data": null, "observations": null, "is_in_staging": null, "is_partition": null, "type": "STRING"}, {"name": "taxa_furto_veiculos", "bigquery_type": null, "description": null, "temporal_coverage": null, "covered_by_dictionary": null, "directory_column": {"dataset_id": null, "table_id": null, "column_name": null}, "measurement_unit": null, "has_sensitive_data": null, "observations": null, "is_in_staging": null, "is_partition": null, "type": "STRING"}, {"name": "taxa_furto_transeunte", "bigquery_type": null, "description": null, "temporal_coverage": null, "covered_by_dictionary": null, "directory_column": {"dataset_id": null, "table_id": null, "column_name": null}, "measurement_unit": null, "has_sensitive_data": null, "observations": null, "is_in_staging": null, "is_partition": null, "type": "STRING"}, {"name": "taxa_furto_coletivo", "bigquery_type": null, "description": null, "temporal_coverage": null, "covered_by_dictionary": null, "directory_column": {"dataset_id": null, "table_id": null, "column_name": null}, "measurement_unit": null, "has_sensitive_data": null, "observations": null, "is_in_staging": null, "is_partition": null, "type": "STRING"}, {"name": "taxa_furto_celular", "bigquery_type": null, "description": null, "temporal_coverage": null, "covered_by_dictionary": null, "directory_column": {"dataset_id": null, "table_id": null, "column_name": null}, "measurement_unit": null, "has_sensitive_data": null, "observations": null, "is_in_staging": null, "is_partition": null, "type": "STRING"}, {"name": "taxa_furto_bicicleta", "bigquery_type": null, "description": null, "temporal_coverage": null, "covered_by_dictionary": null, "directory_column": {"dataset_id": null, "table_id": null, "column_name": null}, "measurement_unit": null, "has_sensitive_data": null, "observations": null, "is_in_staging": null, "is_partition": null, "type": "STRING"}, {"name": "taxa_outros_furtos", "bigquery_type": null, "description": null, "temporal_coverage": null, "covered_by_dictionary": null, "directory_column": {"dataset_id": null, "table_id": null, "column_name": null}, "measurement_unit": null, "has_sensitive_data": null, "observations": null, "is_in_staging": null, "is_partition": null, "type": "STRING"}, {"name": "taxa_total_furtos", "bigquery_type": null, "description": null, "temporal_coverage": null, "covered_by_dictionary": null, "directory_column": {"dataset_id": null, "table_id": null, "column_name": null}, "measurement_unit": null, "has_sensitive_data": null, "observations": null, "is_in_staging": null, "is_partition": null, "type": "STRING"}, {"name": "taxa_sequestro", "bigquery_type": null, "description": null, "temporal_coverage": null, "covered_by_dictionary": null, "directory_column": {"dataset_id": null, "table_id": null, "column_name": null}, "measurement_unit": null, "has_sensitive_data": null, "observations": null, "is_in_staging": null, "is_partition": null, "type": "STRING"}, {"name": "taxa_extorsao", "bigquery_type": null, "description": null, "temporal_coverage": null, "covered_by_dictionary": null, "directory_column": {"dataset_id": null, "table_id": null, "column_name": null}, "measurement_unit": null, "has_sensitive_data": null, "observations": null, "is_in_staging": null, "is_partition": null, "type": "STRING"}, {"name": "taxa_sequestro_relampago", "bigquery_type": null, "description": null, "temporal_coverage": null, "covered_by_dictionary": null, "directory_column": {"dataset_id": null, "table_id": null, "column_name": null}, "measurement_unit": null, "has_sensitive_data": null, "observations": null, "is_in_staging": null, "is_partition": null, "type": "STRING"}, {"name": "taxa_estelionato", "bigquery_type": null, "description": null, "temporal_coverage": null, "covered_by_dictionary": null, "directory_column": {"dataset_id": null, "table_id": null, "column_name": null}, "measurement_unit": null, "has_sensitive_data": null, "observations": null, "is_in_staging": null, "is_partition": null, "type": "STRING"}, {"name": "taxa_apreensao_drogas", "bigquery_type": null, "description": null, "temporal_coverage": null, "covered_by_dictionary": null, "directory_column": {"dataset_id": null, "table_id": null, "column_name": null}, "measurement_unit": null, "has_sensitive_data": null, "observations": null, "is_in_staging": null, "is_partition": null, "type": "STRING"}, {"name": "taxa_registro_posse_drogas", "bigquery_type": null, "description": null, "temporal_coverage": null, "covered_by_dictionary": null, "directory_column": {"dataset_id": null, "table_id": null, "column_name": null}, "measurement_unit": null, "has_sensitive_data": null, "observations": null, "is_in_staging": null, "is_partition": null, "type": "STRING"}, {"name": "taxa_registro_trafico_drogas", "bigquery_type": null, "description": null, "temporal_coverage": null, "covered_by_dictionary": null, "directory_column": {"dataset_id": null, "table_id": null, "column_name": null}, "measurement_unit": null, "has_sensitive_data": null, "observations": null, "is_in_staging": null, "is_partition": null, "type": "STRING"}, {"name": "taxa_registro_apreensao_drogas_sem_autor", "bigquery_type": null, "description": null, "temporal_coverage": null, "covered_by_dictionary": null, "directory_column": {"dataset_id": null, "table_id": null, "column_name": null}, "measurement_unit": null, "has_sensitive_data": null, "observations": null, "is_in_staging": null, "is_partition": null, "type": "STRING"}, {"name": "taxa_registro_veiculo_recuperado", "bigquery_type": null, "description": null, "temporal_coverage": null, "covered_by_dictionary": null, "directory_column": {"dataset_id": null, "table_id": null, "column_name": null}, "measurement_unit": null, "has_sensitive_data": null, "observations": null, "is_in_staging": null, "is_partition": null, "type": "STRING"}, {"name": "taxa_apf", "bigquery_type": null, "description": null, "temporal_coverage": null, "covered_by_dictionary": null, "directory_column": {"dataset_id": null, "table_id": null, "column_name": null}, "measurement_unit": null, "has_sensitive_data": null, "observations": null, "is_in_staging": null, "is_partition": null, "type": "STRING"}, {"name": "taxa_aaapai", "bigquery_type": null, "description": null, "temporal_coverage": null, "covered_by_dictionary": null, "directory_column": {"dataset_id": null, "table_id": null, "column_name": null}, "measurement_unit": null, "has_sensitive_data": null, "observations": null, "is_in_staging": null, "is_partition": null, "type": "STRING"}, {"name": "taxa_cmp", "bigquery_type": null, "description": null, "temporal_coverage": null, "covered_by_dictionary": null, "directory_column": {"dataset_id": null, "table_id": null, "column_name": null}, "measurement_unit": null, "has_sensitive_data": null, "observations": null, "is_in_staging": null, "is_partition": null, "type": "STRING"}, {"name": "taxa_cmba", "bigquery_type": null, "description": null, "temporal_coverage": null, "covered_by_dictionary": null, "directory_column": {"dataset_id": null, "table_id": null, "column_name": null}, "measurement_unit": null, "has_sensitive_data": null, "observations": null, "is_in_staging": null, "is_partition": null, "type": "STRING"}, {"name": "taxa_ameaca", "bigquery_type": null, "description": null, "temporal_coverage": null, "covered_by_dictionary": null, "directory_column": {"dataset_id": null, "table_id": null, "column_name": null}, "measurement_unit": null, "has_sensitive_data": null, "observations": null, "is_in_staging": null, "is_partition": null, "type": "STRING"}, {"name": "taxa_pessoas_desaparecidas", "bigquery_type": null, "description": null, "temporal_coverage": null, "covered_by_dictionary": null, "directory_column": {"dataset_id": null, "table_id": null, "column_name": null}, "measurement_unit": null, "has_sensitive_data": null, "observations": null, "is_in_staging": null, "is_partition": null, "type": "STRING"}, {"name": "taxa_encontro_cadaver", "bigquery_type": null, "description": null, "temporal_coverage": null, "covered_by_dictionary": null, "directory_column": {"dataset_id": null, "table_id": null, "column_name": null}, "measurement_unit": null, "has_sensitive_data": null, "observations": null, "is_in_staging": null, "is_partition": null, "type": "STRING"}, {"name": "taxa_encontro_ossada", "bigquery_type": null, "description": null, "temporal_coverage": null, "covered_by_dictionary": null, "directory_column": {"dataset_id": null, "table_id": null, "column_name": null}, "measurement_unit": null, "has_sensitive_data": null, "observations": null, "is_in_staging": null, "is_partition": null, "type": "STRING"}, {"name": "taxa_policial_militar_morto_servico", "bigquery_type": null, "description": null, "temporal_coverage": null, "covered_by_dictionary": null, "directory_column": {"dataset_id": null, "table_id": null, "column_name": null}, "measurement_unit": null, "has_sensitive_data": null, "observations": null, "is_in_staging": null, "is_partition": null, "type": "STRING"}, {"name": "taxa_policial_civil_morto_servico", "bigquery_type": null, "description": null, "temporal_coverage": null, "covered_by_dictionary": null, "directory_column": {"dataset_id": null, "table_id": null, "column_name": null}, "measurement_unit": null, "has_sensitive_data": null, "observations": null, "is_in_staging": null, "is_partition": null, "type": "STRING"}, {"name": "taxa_registro_ocorrencia", "bigquery_type": null, "description": null, "temporal_coverage": null, "covered_by_dictionary": null, "directory_column": {"dataset_id": null, "table_id": null, "column_name": null}, "measurement_unit": null, "has_sensitive_data": null, "observations": null, "is_in_staging": null, "is_partition": null, "type": "STRING"}, {"name": "tipo_fase", "bigquery_type": null, "description": null, "temporal_coverage": null, "covered_by_dictionary": null, "directory_column": {"dataset_id": null, "table_id": null, "column_name": null}, "measurement_unit": null, "has_sensitive_data": null, "observations": null, "is_in_staging": null, "is_partition": null, "type": "STRING"}]